cepact/__init__.py
cepact/cepact.py
cepact/conf.py
cepact/misc.py
cepact/input_processor/__init__.py
cepact/input_processor/abstract_fetchers.py
cepact/input_processor/input_processor.py
cepact/input_processor/concrete_fetchers/__init__.py
cepact/input_processor/concrete_fetchers/grafana_fetcher.py
cepact/input_processor/concrete_fetchers/influx_fetcher.py
cepact/input_processor/concrete_fetchers/local_ann_params_fetcher.py
cepact/input_processor/concrete_fetchers/local_discretization_fetcher.py
cepact/input_processor/concrete_fetchers/local_ign_sensor_fetcher.py
cepact/input_processor/concrete_fetchers/local_signature_fetcher.py
cepact/input_processor/concrete_fetchers/static/ignore_sensors_schema.json
cepact/input_processor/concrete_fetchers/static/timeseries_schema.json
cepact/output_producer/__init__.py
cepact/output_producer/abstract_instance_level_det_query.py
cepact/output_producer/concrete_instance_level_det_queries.py
cepact/output_producer/output_producer.py
cepact/output_producer/siddhi_producer.py
cepact/output_producer/sink_source_pattern_helper.py
cepact/representations/__init__.py
cepact/representations/activity.py
cepact/representations/annotation_params.py
cepact/representations/changes.py
cepact/representations/discretization.py
cepact/representations/signature.py
cepact-0.1.1.dist-info/licenses/AUTHORS.md
cepact-0.1.1.dist-info/licenses/LICENSE
cepact-0.1.1.dist-info/METADATA
cepact-0.1.1.dist-info/WHEEL
cepact-0.1.1.dist-info/top_level.txt
cepact-0.1.1.dist-info/RECORD
