Metadata-Version: 2.4
Name: cepact
Version: 0.1.1
Summary: Create CEP activity detection services from expert annotations and IoT data.
Home-page: https://github.com/ics-unisg/activity-detection-services-generator
Author: "ICS, University of St.Gallen"
Author-email: "aaron.kurz@unisg.ch"
License: GNU Affero General Public License v3 (AGPLv3)
Project-URL: Bug Tracker, https://github.com/ics-unisg/activity-detection-services-generator/issues
Keywords: activity detection,iot,pattern recognition,domain experts,smart factory
Classifier: Development Status :: 4 - Beta
Classifier: Intended Audience :: Science/Research
Classifier: License :: OSI Approved :: GNU Affero General Public License v3
Classifier: Programming Language :: Python :: 3.12
Classifier: Topic :: Scientific/Engineering
Requires-Python: >=3.12
License-File: LICENSE
License-File: AUTHORS.md
Requires-Dist: requests~=2.32.3
Requires-Dist: pandas~=2.2.3
Requires-Dist: influxdb_client==1.48.0
Requires-Dist: jsonschema~=4.23.0
Provides-Extra: testing
Requires-Dist: pytest>=3; extra == "testing"
Dynamic: license-file
